up2b/__init__.py
up2b/__main__.py
up2b/py.typed
up2b/version.py
up2b/up2b_lib/__init__.py
up2b/up2b_lib/cache.py
up2b/up2b_lib/compress.py
up2b/up2b_lib/constants.py
up2b/up2b_lib/custom_types.py
up2b/up2b_lib/errors.py
up2b/up2b_lib/file.py
up2b/up2b_lib/http.py
up2b/up2b_lib/i18n.py
up2b/up2b_lib/log.py
up2b/up2b_lib/py.typed
up2b/up2b_lib/utils.py
up2b/up2b_lib/watermark.py
up2b/up2b_lib/up2b_api/__init__.py
up2b/up2b_lib/up2b_api/__init__.pyi
up2b/up2b_lib/up2b_api/github.py
up2b/up2b_lib/up2b_api/imgtg.py
up2b/up2b_lib/up2b_api/imgtu.py
up2b/up2b_lib/up2b_api/py.typed
up2b/up2b_lib/up2b_api/sm.py
up2b-0.7.1.dist-info/LICENSE
up2b-0.7.1.dist-info/METADATA
up2b-0.7.1.dist-info/WHEEL
up2b-0.7.1.dist-info/entry_points.txt
up2b-0.7.1.dist-info/top_level.txt
up2b-0.7.1.dist-info/RECORD
