Metadata-Version: 2.1
Name: up2b
Version: 0.7.1
Summary: 上传图片到图床
Author-email: thep0y <thepoy@163.com>
License: MIT License
Project-URL: homepage, https://github.com/thep0y/up2b
Project-URL: repository, https://github.com/thep0y/up2b
Keywords: typora,image bed,upload,picture bed,图床
Classifier: Programming Language :: Python :: 3
Requires-Python: >=3
License-File: LICENSE
Requires-Dist: requests
Requires-Dist: click
Requires-Dist: colorful-logger >=0.2.0
Requires-Dist: tqdm
Requires-Dist: requests-toolbelt
Requires-Dist: typing-extensions ; python_version < "3.8"
Provides-Extra: mark
Requires-Dist: pillow ; extra == 'mark'
